{
  "lastUpdated": "2026-07-17T09:07:04.303Z",
  "posts": [
    {
      "id": "tt_7643419710742170888",
      "platform": "tiktok",
      "url": "https://www.tiktok.com/@nonelikekay/video/7643419710742170888",
      "thumbnail": "https://p16-common-sign.tiktokcdn.com/tos-alisg-p-0037/oMIgSq7EPBu9lgREfBIAwFEBF4DqiEDOjflUcU~tplv-tiktokx-origin.image?dr=14575&x-expires=1784451600&x-signature=wkNdL%2FhJmNGzQUwbqIDtK%2BLXTJU%3D&t=4d5b0474&ps=13740610&shp=81f88b70&shcp=43f4a2f9&idc=my2",
      "creator": "nonelikekay",
      "caption": "Ula Beach Club, a new spot in Accra, boasts a visually stunning setting with breathtaking ocean views. While the ambianc",
      "likes": 176900,
      "hashtags": [
        "ghanatiktok🇬🇭",
        "fyp"
      ],
      "postedAt": "2026-05-24T11:32:16.000Z"
    },
    {
      "id": "tt_7650982286778699015",
      "platform": "tiktok",
      "url": "https://www.tiktok.com/@onlyonemanassa/video/7650982286778699015",
      "thumbnail": "https://p16-common-sign.tiktokcdn-us.com/tos-alisg-p-0037/ocgGotAcAJFvRJ4VOJfG4XAAICwe23AQxAeLGf~tplv-tiktokx-origin.image?dr=9636&x-expires=1784451600&x-signature=xlgFdc9XuZZxscQyGzrcx1BAzYg%3D&t=4d5b0474&ps=13740610&shp=81f88b70&shcp=43f4a2f9&idc=useast5",
      "creator": "onlyonemanassa",
      "caption": "Ghana is sweet ooo🇬🇭 and these are the places you will never forget💞\n\nThis was my grandma’s first time experiencing s",
      "likes": 84400,
      "hashtags": [
        {
          "name": ""
        }
      ],
      "postedAt": "2026-06-13T20:39:00.000Z"
    },
    {
      "id": "tt_7598981525589347615",
      "platform": "tiktok",
      "url": "https://www.tiktok.com/@alexis_nikohl/video/7598981525589347615",
      "thumbnail": "https://p16-common-sign.tiktokcdn-us.com/tos-useast8-p-0068-tx2/ocdaCSADeAEQAUGnIaeqm8QAOLjag6BA7qIIIe~tplv-tiktokx-origin.image?dr=9636&x-expires=1784451600&x-signature=Urb8eyHdhb6Dmkz5LjA7j3SDAXE%3D&t=4d5b0474&ps=13740610&shp=81f88b70&shcp=43f4a2f9&idc=useast5",
      "creator": "alexis_nikohl",
      "caption": "Here’s everything I did in Accra, Ghana 💕💚🇬🇭 I’ll be back for a personal trip. Comment recommendations for next time",
      "likes": 35900,
      "hashtags": [
        "alphakappaalpha",
        "ghanatiktok🇬🇭",
        "traveltok",
        "fyp"
      ],
      "postedAt": "2026-01-24T17:29:39.000Z"
    },
    {
      "id": "tt_7653873287390317844",
      "platform": "tiktok",
      "url": "https://www.tiktok.com/@keishasescapade/video/7653873287390317844",
      "thumbnail": "https://p16-common-sign.tiktokcdn-us.com/tos-alisg-p-0037/oQcBOVBYigVeOB42OR9RABUEj2bIIUDfgqAxAi~tplv-tiktokx-origin.image?dr=9636&x-expires=1784451600&x-signature=8PPtboBmdfaaSudelTjQrbBAqD0%3D&t=4d5b0474&ps=13740610&shp=81f88b70&shcp=43f4a2f9&idc=useast5",
      "creator": "keishasescapade",
      "caption": "Enjoyment minister is back!🙂‍↔️🥂\nDay 1 at OUTSKIRTSRESORT was fabulous!😍\nI can’t wait to show you all I did the next ",
      "likes": 33400,
      "hashtags": [
        {
          "name": ""
        },
        "fyp",
        "ghanatiktok🇬🇭",
        "hiddengems",
        "tour",
        "explore"
      ],
      "postedAt": "2026-06-21T15:37:30.000Z"
    },
    {
      "id": "tt_7662798980157410580",
      "platform": "tiktok",
      "url": "https://www.tiktok.com/@janiceziem/video/7662798980157410580",
      "thumbnail": "https://p16-common-sign.tiktokcdn-us.com/tos-alisg-p-0037/okfERCFVTIDxU6AAsmAgfMEtqvQmRIjBcAi7dC~tplv-tiktokx-origin.image?dr=9636&x-expires=1784451600&x-signature=SmNVZRz0CPP28qsa2rXpXhfRycw%3D&t=4d5b0474&ps=13740610&shp=81f88b70&shcp=43f4a2f9&idc=useast5",
      "creator": "janiceziem",
      "caption": "@Sea View Cabana 📍\n\nDay Visit (No Overnight Stay)\nGH₵600 per person\nIncludes access to the amenities, one meal, and one",
      "likes": 28100,
      "hashtags": [
        {
          "name": ""
        },
        "ghanatiktok🇬🇭",
        "seaviewcabana",
        "vacation",
        "airbnb",
        "janiceziem"
      ],
      "postedAt": "2026-07-15T16:53:45.000Z"
    },
    {
      "id": "tt_7618557425167256833",
      "platform": "tiktok",
      "url": "https://www.tiktok.com/@keishasescapade/video/7618557425167256833",
      "thumbnail": "https://p16-common-sign.tiktokcdn-us.com/tos-alisg-p-0037/oMDSeMIIIDATLydefjL469262dkwmIAqGCRjKx~tplv-tiktokx-origin.image?dr=9636&x-expires=1784451600&x-signature=dL42NxGNCQcEmLSKePbacpQqoZE%3D&t=4d5b0474&ps=13740610&shp=81f88b70&shcp=43f4a2f9&idc=useast5",
      "creator": "keishasescapade",
      "caption": "The long awaited vlog is here darlings😍Did you enjoy it ?🤭\nAfro Breeze \n(March 2026 )Room Rate : ¢1800 per night . ( f",
      "likes": 27900,
      "hashtags": [
        "fyp",
        "ghanatiktok🇬🇭",
        "hiddengems",
        "tour",
        "explore"
      ],
      "postedAt": "2026-03-18T11:34:05.000Z"
    },
    {
      "id": "tt_7652798013273804052",
      "platform": "tiktok",
      "url": "https://www.tiktok.com/@darasimiogbetah/video/7652798013273804052",
      "thumbnail": "https://p16-common-sign.tiktokcdn-us.com/tos-alisg-p-0037/ogDqB0mZEO0FmcMAWgoINVuyRKofDBD6Ef0Ipc~tplv-tiktokx-origin.image?dr=9636&x-expires=1784451600&x-signature=wD6RINNdcBpeM9eDxTM%2F7VKx5Cc%3D&t=4d5b0474&ps=13740610&shp=81f88b70&shcp=43f4a2f9&idc=useast5",
      "creator": "darasimiogbetah",
      "caption": "Day 1 in Ghana!🇬🇭✈️🌴\n\n#Ghana #BirthdayTrip ",
      "likes": 16500,
      "hashtags": [
        "ghana",
        "birthdaytrip"
      ],
      "postedAt": "2026-06-18T18:04:52.000Z"
    },
    {
      "id": "tt_7576975219806588167",
      "platform": "tiktok",
      "url": "https://www.tiktok.com/@kojo.living/video/7576975219806588167",
      "thumbnail": "https://p19-common-sign.tiktokcdn-us.com/tos-alisg-p-0037/oAbVRAQ0mYJ6cIPiQEIBy5BviaClASyuI8Igc~tplv-tiktokx-origin.image?dr=9636&x-expires=1784451600&x-signature=ZcnNUVFuXWKpq0nfc569oFQN63k%3D&t=4d5b0474&ps=13740610&shp=81f88b70&shcp=43f4a2f9&idc=useast5",
      "creator": "kojo.living",
      "caption": "Ghana in December is a whole new world of music, culture, beaches, food + unforgettable experiences.\nIf you’ve been drea",
      "likes": 14400,
      "hashtags": [
        "ghanaindecember",
        "accravibes",
        "kojolivingexperience",
        "dettydecember",
        "visitghana",
        "diasporareturning",
        "africatotheworld"
      ],
      "postedAt": "2025-11-26T10:13:41.000Z"
    },
    {
      "id": "tt_7560736804127689996",
      "platform": "tiktok",
      "url": "https://www.tiktok.com/@_mtravels_/video/7560736804127689996",
      "thumbnail": "https://p16-common-sign.tiktokcdn-us.com/tos-maliva-p-0068/oIIOtoUEpBSnFQRevaIA7FEBGIDd07IsKfB0hJ~tplv-tiktokx-origin.image?dr=9636&x-expires=1784451600&x-signature=HWZ7DYDK1%2BAmlo7Me7zmL3ZudeE%3D&t=4d5b0474&ps=13740610&shp=81f88b70&shcp=43f4a2f9&idc=useast5",
      "creator": "_mtravels_",
      "caption": "✅Save this list!\nGhana isn’t boring, you just don’t know what to do. Here’s a list of activities I think you’d love. Per",
      "likes": 13800,
      "hashtags": [
        "tiktokghana🇬🇭",
        "fyp",
        "thingstodo",
        "activities",
        "travel"
      ],
      "postedAt": "2025-10-13T16:00:24.000Z"
    },
    {
      "id": "tt_7356217160823246085",
      "platform": "tiktok",
      "url": "https://www.tiktok.com/@visitghananow/video/7356217160823246085",
      "thumbnail": "https://p16-common-sign.tiktokcdn.com/tos-maliva-i-e1os8tt47a-us/bd10a3c853204ae183108fce340ae0cc~tplv-tiktokx-origin.image?dr=14575&x-expires=1784451600&x-signature=yPlaDqqMa84Vsto0GYLCXOEfYhw%3D&t=4d5b0474&ps=13740610&shp=81f88b70&shcp=43f4a2f9&idc=my",
      "creator": "visitghananow",
      "caption": "American hip hop artist Ja Rule cist #kwamenkrumahmemorialpark @Beyond the Return @Trending Video #visitghana #tiktokgha",
      "likes": 13800,
      "hashtags": [
        "kwamenkrumahmemorialpark",
        {
          "name": ""
        },
        {
          "name": ""
        },
        "visitghana",
        "tiktokghana🇬🇭",
        "jarule",
        "knmp",
        "kwamenkrumah",
        "tiktokusa"
      ],
      "postedAt": "2024-04-10T12:39:39.000Z"
    },
    {
      "id": "tt_7343874124885888299",
      "platform": "tiktok",
      "url": "https://www.tiktok.com/@hey_ciara/video/7343874124885888299",
      "thumbnail": "https://p19-common-sign.tiktokcdn-us.com/tos-useast5-p-0068-tx/o863ry4rPAAzDoBTCqoquAIw6iIiqewcXpiEBO~tplv-tiktokx-origin.image?dr=9636&x-expires=1784451600&x-signature=FyuYfuOG6t0Wq2TdMVpwJxy%2B6rw%3D&t=4d5b0474&ps=13740610&shp=81f88b70&shcp=43f4a2f9&idc=useast5",
      "creator": "hey_ciara",
      "caption": "Replying to @Jasmine • adventure travel itinerary next up! #dettydecember #traveltok #traveltiktok #ghana #westafrica #b",
      "likes": 11900,
      "hashtags": [
        {
          "name": ""
        },
        "dettydecember",
        "traveltok",
        "traveltiktok",
        "ghana",
        "westafrica",
        "blacktravel",
        "dettydecember"
      ],
      "postedAt": "2024-03-08T06:22:33.000Z"
    },
    {
      "id": "tt_7520583781246389560",
      "platform": "tiktok",
      "url": "https://www.tiktok.com/@ghanagetaways/video/7520583781246389560",
      "thumbnail": "https://p16-common-sign.tiktokcdn.com/tos-maliva-p-0068/oE2WzDqQ2uFnBFDfEQv83JoyeiRgXAcLEQcBHP~tplv-tiktokx-origin.image?dr=14575&x-expires=1784451600&x-signature=jQbxMo38VNBLKiUwyAlFjCxiegc%3D&t=4d5b0474&ps=13740610&shp=81f88b70&shcp=43f4a2f9&idc=my",
      "creator": "ghanagetaways",
      "caption": "Peaceful road trip to the highest settlement in Ghana #ghanagetaways #hiking #beautifuldestinations #placestovisit ",
      "likes": 9572,
      "hashtags": [
        "ghanagetaways",
        "hiking",
        "beautifuldestinations",
        "placestovisit"
      ],
      "postedAt": "2025-06-27T11:06:09.000Z"
    },
    {
      "id": "tt_7583653360721595662",
      "platform": "tiktok",
      "url": "https://www.tiktok.com/@bjackpov/video/7583653360721595662",
      "thumbnail": "https://p16-common-sign.tiktokcdn-us.com/tos-useast5-p-0068-tx/osL5eAGfAjBOQLG3kzcRoAIRAIseJViQAApRIe~tplv-tiktokx-origin.image?dr=9636&x-expires=1784451600&x-signature=RINNN4kTmKJg%2B0E74fIf6va%2BzuI%3D&t=4d5b0474&ps=13740610&shp=81f88b70&shcp=43f4a2f9&idc=useast5",
      "creator": "bjackpov",
      "caption": "it’s a lot more to be added to this list butttttt this my top 9 + a bonus at the end\n\n#dettydecember #ghanatiktok #trave",
      "likes": 8671,
      "hashtags": [
        "dettydecember",
        "ghanatiktok",
        "travel",
        "fyppp"
      ],
      "postedAt": "2025-12-14T10:10:18.000Z"
    },
    {
      "id": "tt_7661724195415493889",
      "platform": "tiktok",
      "url": "https://www.tiktok.com/@nalu.hideaways.gh/video/7661724195415493889",
      "thumbnail": "https://p16-common-sign.tiktokcdn-us.com/tos-alisg-p-0037/ooEibCap9Vl0YmhP3wIvAdvlBATuimBp63XPI~tplv-tiktokx-origin.image?dr=9636&x-expires=1784451600&x-signature=nZ5s5916mRz1LLD%2FTXXhutt0N%2Fg%3D&t=4d5b0474&ps=13740610&shp=81f88b70&shcp=43f4a2f9&idc=useast5",
      "creator": "nalu.hideaways.gh",
      "caption": "Save this for your next beach getaway🌴✨ Tag someone you’d bring with you 🩵 #traveltiktok #travellife #hiddengems #ghan",
      "likes": 8459,
      "hashtags": [
        "traveltiktok",
        "travellife",
        "hiddengems",
        "ghana",
        "explorepage"
      ],
      "postedAt": "2026-07-12T19:23:34.000Z"
    },
    {
      "id": "tt_7659884194251820309",
      "platform": "tiktok",
      "url": "https://www.tiktok.com/@jerrison.fts/video/7659884194251820309",
      "thumbnail": "https://p16-common-sign.tiktokcdn-us.com/tos-alisg-p-0037/oUUDcAAAECeAQEFgqN9AjwWfMAiRChETaIBirV~tplv-tiktokx-dmt-logom:tos-alisg-i-0068/oQYeMFCIEIBEANmRsNfAnAfAjAt8UDodDAvBEj.image?dr=9634&x-expires=1784451600&x-signature=BVPQ4sbKKx2umWAsYeVB0qqn2Xg%3D&t=4d5b0474&ps=13740610&shp=81f88b70&shcp=43f4a2f9&idc=useast5",
      "creator": "jerrison.fts",
      "caption": "Looking for a place to stay in atimpoku ? Tag your Besties and homeboys . More details will be posted soon . All places ",
      "likes": 8106,
      "hashtags": [
        "ghanatiktok🇬🇭",
        "akosombo",
        "atimpoku",
        "resort",
        "airbnb"
      ],
      "postedAt": "2026-07-07T20:22:59.000Z"
    },
    {
      "id": "tt_7628717110163770638",
      "platform": "tiktok",
      "url": "https://www.tiktok.com/@ayeyiathome/video/7628717110163770638",
      "thumbnail": "https://p16-common-sign.tiktokcdn-us.com/tos-useast5-p-0068-tx/osBNpqP1DQmmCenRA0FgS4RppBfMpCDQESg7E3~tplv-tiktokx-origin.image?dr=9636&x-expires=1784451600&x-signature=9EmU3HQIB%2BC7eOW%2BfxpM0KePRes%3D&t=4d5b0474&ps=13740610&shp=81f88b70&shcp=43f4a2f9&idc=useast5",
      "creator": "ayeyiathome",
      "caption": "Me 🤝🏿 traveling in style 😎 No matter where in the world I go, I love staying at the best of the best! @Crown Lusso Lt",
      "likes": 5088,
      "hashtags": [
        {
          "name": ""
        },
        "accra",
        "ghana",
        "accrahotels",
        "ghanaapartments",
        "ghanahotels"
      ],
      "postedAt": "2026-04-14T20:38:59.000Z"
    },
    {
      "id": "tt_7632617449564671253",
      "platform": "tiktok",
      "url": "https://www.tiktok.com/@ghanagetaways/video/7632617449564671253",
      "thumbnail": "https://p16-common-sign.tiktokcdn.com/tos-alisg-p-0037/owUg7EuRgI0UEgwBEpIgKDDeFmfDABTorI8sjc~tplv-tiktokx-origin.image?dr=14575&x-expires=1784451600&x-signature=hZyrNz6TdJL%2B0Ay16vg7C8zGC5o%3D&t=4d5b0474&ps=13740610&shp=81f88b70&shcp=43f4a2f9&idc=my",
      "creator": "ghanagetaways",
      "caption": "Eastern Region Ghana ",
      "likes": 4486,
      "hashtags": [],
      "postedAt": "2026-04-25T08:54:01.000Z"
    },
    {
      "id": "tt_7368630171248758022",
      "platform": "tiktok",
      "url": "https://www.tiktok.com/@ghanagetaways/video/7368630171248758022",
      "thumbnail": "https://p16-common-sign.tiktokcdn.com/tos-maliva-p-0068/osfRIEFDUu2ZKL8Fs7BeQFcRQDFDBmAqQdDJrE~tplv-tiktokx-origin.image?dr=14575&x-expires=1784451600&x-signature=IU9zkR1c7M9CAQuNYzlMY4iJzxg%3D&t=4d5b0474&ps=13740610&shp=81f88b70&shcp=43f4a2f9&idc=my",
      "creator": "ghanagetaways",
      "caption": "Explore Ghana with us, send us a message.\nGet ready for more adventures \n#ghana #explorer #exploreghana #placestovisit #",
      "likes": 3661,
      "hashtags": [
        "ghana",
        "explorer",
        "exploreghana",
        "placestovisit",
        "beautifuldestinations",
        "visitghana",
        "travelghana"
      ],
      "postedAt": "2024-05-13T23:28:30.000Z"
    },
    {
      "id": "tt_7426825500238122246",
      "platform": "tiktok",
      "url": "https://www.tiktok.com/@ghanagetaways/video/7426825500238122246",
      "thumbnail": "https://p16-common-sign.tiktokcdn.com/tos-maliva-p-0068/o00MICALnEdccjEgfnIINLIsFfYrGeMCSnMOpR~tplv-tiktokx-origin.image?dr=14575&x-expires=1784451600&x-signature=2HRhao4my0q6tg7LNDHZwZvNJt0%3D&t=4d5b0474&ps=13740610&shp=81f88b70&shcp=43f4a2f9&idc=my",
      "creator": "ghanagetaways",
      "caption": "And of course we had to celebrate at their local bar💀🤌🏾 #vacations #touristattraction #tourisminghana #westafrica #pl",
      "likes": 3180,
      "hashtags": [
        "vacations",
        "touristattraction",
        "tourisminghana",
        "westafrica",
        "placestovisitinghana",
        "nzulenzu",
        "nzulenzuvillage",
        "nzulezu"
      ],
      "postedAt": "2024-10-17T19:16:09.000Z"
    },
    {
      "id": "tt_7590115490828275000",
      "platform": "tiktok",
      "url": "https://www.tiktok.com/@tripsghana/video/7590115490828275000",
      "thumbnail": "https://p16-common-sign.tiktokcdn.com/tos-maliva-p-0068/okGlgpRtfAByD6DVEdRVDDQQlFRqYVRfbJEIBK~tplv-tiktokx-origin.image?dr=14575&x-expires=1784451600&x-signature=8b0fox6cP6r4ONMOIYfY%2FxEGsXE%3D&t=4d5b0474&ps=13740610&shp=81f88b70&shcp=43f4a2f9&idc=my",
      "creator": "tripsghana",
      "caption": "Some friends like enemies @Yhaw Birth @𝐁𝐚𝐧𝐲🕊️🎧 @Virginboy🇬🇭🌍 @Bisa Kdei @She is pretty❤️❤️💕😇🌺🌷🌷 manager @K",
      "likes": 2291,
      "hashtags": [
        {
          "name": ""
        },
        {
          "name": ""
        },
        {
          "name": ""
        },
        {
          "name": ""
        },
        {
          "name": ""
        },
        {
          "name": ""
        },
        "capcut"
      ],
      "postedAt": "2025-12-31T20:04:43.000Z"
    },
    {
      "id": "tt_7633037122303200543",
      "platform": "tiktok",
      "url": "https://www.tiktok.com/@gigiknowsbest1/video/7633037122303200543",
      "thumbnail": "https://p16-common-sign.tiktokcdn-us.com/tos-useast8-p-0068-tx2/oEAAIIwTqENAAjrQ8ybfEFf2HDI1EfIhH2HT3A~tplv-tiktokx-origin.image?dr=9636&x-expires=1784451600&x-signature=dWJpHAGUVa6gbEosAMNRzEkkkxs%3D&t=4d5b0474&ps=13740610&shp=81f88b70&shcp=43f4a2f9&idc=useast5",
      "creator": "gigiknowsbest1",
      "caption": "Ghana vlog Accra #fypシ #ghanatiktok🇬🇭 ",
      "likes": 1881,
      "hashtags": [
        "fypシ",
        "ghanatiktok🇬🇭"
      ],
      "postedAt": "2026-04-26T12:03:28.000Z"
    },
    {
      "id": "tt_7638682958181731591",
      "platform": "tiktok",
      "url": "https://www.tiktok.com/@premiumtravel0/video/7638682958181731591",
      "thumbnail": "https://p19-common-sign.tiktokcdn-us.com/tos-alisg-p-0037/oshCb1ZBiBJQAiU4tJuI5wADgT7AAvB4CIcfI6~tplv-tiktokx-origin.image?dr=9636&x-expires=1784451600&x-signature=1uxtzn%2FQ9VjtiveBEE735znVHt0%3D&t=4d5b0474&ps=13740610&shp=81f88b70&shcp=43f4a2f9&idc=useast5",
      "creator": "premiumtravel0",
      "caption": "🚨🇬🇭 Le Ghana est trop sous-coté… jusqu’à ce que tu y mettes les pieds 😭🔥\n\nEntre les cascades 💦\nles beach clubs 🌴\n",
      "likes": 1626,
      "hashtags": [
        "ghanatrip",
        "accravibes",
        "pourtoi",
        "premiumtravel",
        "fyp"
      ],
      "postedAt": "2026-05-11T17:11:18.000Z"
    },
    {
      "id": "tt_7652415595169811730",
      "platform": "tiktok",
      "url": "https://www.tiktok.com/@carmenxcaramelx/video/7652415595169811730",
      "thumbnail": "https://p16-common-sign.tiktokcdn.com/tos-alisg-p-0037/oMQM9RBqcMlrYFSfiyBDvgUEUrBfAYFBoQbEEt~tplv-tiktokx-origin.image?dr=14575&x-expires=1784451600&x-signature=kJlfWdpgJOwC%2B8qQ0XYhl51XiD4%3D&t=4d5b0474&ps=13740610&shp=81f88b70&shcp=43f4a2f9&idc=my2",
      "creator": "carmenxcaramelx",
      "caption": "The best beaches are in the West 🇬🇭 \n\n#axim#ghana#ghanatravel#ghanatiktok#westafrica ",
      "likes": 1484,
      "hashtags": [
        "axim",
        "ghana",
        "ghanatravel",
        "ghanatiktok",
        "westafrica"
      ],
      "postedAt": "2026-06-17T17:21:01.000Z"
    },
    {
      "id": "tt_7598254435864694029",
      "platform": "tiktok",
      "url": "https://www.tiktok.com/@_estherlauren_/video/7598254435864694029",
      "thumbnail": "https://p16-common-sign.tiktokcdn-us.com/tos-useast5-p-0068-tx/ooBAAb4uliBAnCTAE0iB8EfwIA2NwYV1BJymgI~tplv-tiktokx-origin.image?dr=9636&x-expires=1784451600&x-signature=DZN%2F4KbriaGQBU1hCLHS7uaHNUk%3D&t=4d5b0474&ps=13740610&shp=81f88b70&shcp=43f4a2f9&idc=useast5",
      "creator": "_estherlauren_",
      "caption": "Who says you can’t go to Detty December solo ? ✨ #ghanatiktok🇬🇭 #dettydecember #solotravel #solotrip ",
      "likes": 1081,
      "hashtags": [
        "ghanatiktok🇬🇭",
        "dettydecember",
        "solotravel",
        "solotrip"
      ],
      "postedAt": "2026-01-22T18:28:30.000Z"
    },
    {
      "id": "tt_7638704070999444754",
      "platform": "tiktok",
      "url": "https://www.tiktok.com/@beauty_in_business2.0/video/7638704070999444754",
      "thumbnail": "https://p16-common-sign.tiktokcdn-us.com/tos-alisg-p-0037/osYDBI75IIE4pPlDpYaiBCBVPtigAUgLUzIAg~tplv-tiktokx-origin.image?dr=9636&x-expires=1784451600&x-signature=6VN%2BwxDM5wi12Z7D8ChRrLZdeZM%3D&t=4d5b0474&ps=13740610&shp=81f88b70&shcp=43f4a2f9&idc=useast5",
      "creator": "beauty_in_business2.0",
      "caption": "Save this post for later for your weekend getaway.\n📍Eli Beach Resort \nLocated in the Volta Region of Ghana, Keta.\n\nReco",
      "likes": 1045,
      "hashtags": [
        "placestovisit",
        "ghanatiktok🇬🇭",
        "elibeachresort",
        "fyp",
        "viralvideo"
      ],
      "postedAt": "2026-05-11T18:33:13.000Z"
    },
    {
      "id": "tt_7659636370146725150",
      "platform": "tiktok",
      "url": "https://www.tiktok.com/@jay.saint1/video/7659636370146725150",
      "thumbnail": "https://p16-common-sign.tiktokcdn-us.com/tos-useast8-p-0068-tx2/oAdqTADVIECEACvIfEAAQNAFJHYDw8R7sn9RVf~tplv-tiktokx-origin.image?dr=9636&x-expires=1784451600&x-signature=j82cd53HZXf7ZSj3xuMh5IkubjQ%3D&t=4d5b0474&ps=13740610&shp=81f88b70&shcp=43f4a2f9&idc=useast5",
      "creator": "jay.saint1",
      "caption": "Day 2 of our trip to Ghana. Visiting Cape Coast Castle was a life changing experience #capecoastghana #ghana #traveltok ",
      "likes": 976,
      "hashtags": [
        "capecoastghana",
        "ghana",
        "traveltok"
      ],
      "postedAt": "2026-07-07T04:21:25.000Z"
    },
    {
      "id": "tt_7621674728146701582",
      "platform": "tiktok",
      "url": "https://www.tiktok.com/@youadoremunchkn/video/7621674728146701582",
      "thumbnail": "https://p16-common-sign.tiktokcdn-us.com/tos-useast5-p-0068-tx/okA4DGAoaEc3oEXCBhIEaFiABWAPnmMkicPgq~tplv-tiktokx-origin.image?dr=9636&x-expires=1784451600&x-signature=9kv4oLgUKAILFsyO%2FDElef5DIl0%3D&t=4d5b0474&ps=13740610&shp=81f88b70&shcp=43f4a2f9&idc=useast5",
      "creator": "youadoremunchkn",
      "caption": "If you love weekend trips this one is for you! Here’s how to spend 72 hours in Accra Ghana 🇬🇭 \n\n#creatorsearchinsights",
      "likes": 940,
      "hashtags": [
        "creatorsearchinsights",
        "thingstodoinghana",
        "thingstodoinaccra",
        "americanexpats",
        "accrafoodie"
      ],
      "postedAt": "2026-03-26T21:10:47.000Z"
    },
    {
      "id": "tt_7658435283813240071",
      "platform": "tiktok",
      "url": "https://www.tiktok.com/@millibabsie/video/7658435283813240071",
      "thumbnail": "https://p16-common-sign.tiktokcdn-us.com/tos-alisg-p-0037/oQlII1AdJBDiCOyJAAIA3y0fq7UwtiEBAHIBZB~tplv-tiktokx-dmt-logom:tos-alisg-i-0068/oASkM8upIQNgIlOefAUAXEyIEWjHAApeBDTAPZ.image?dr=9634&x-expires=1784451600&x-signature=W%2FJcjymWTFbarKWzNs3CCF%2BwPq0%3D&t=4d5b0474&ps=13740610&shp=81f88b70&shcp=43f4a2f9&idc=useast5",
      "creator": "millibabsie",
      "caption": "Weekend therapy looks a lot like this. ✨🌴 #AhantaWavesResort \n#weekendgetaway #fyp #westernregion  #VisitGhana",
      "likes": 725,
      "hashtags": [
        "ahantawavesresort",
        "weekendgetaway",
        "fyp",
        "westernregion",
        "visitghana"
      ],
      "postedAt": "2026-07-03T22:40:24.000Z"
    },
    {
      "id": "tt_7574655852834065675",
      "platform": "tiktok",
      "url": "https://www.tiktok.com/@ghanatravel0/video/7574655852834065675",
      "thumbnail": "https://p16-common-sign.tiktokcdn.com/tos-maliva-p-0068/oEqeJQrQnDj9BgIQrCXSAl4MgcSgeCLX8SPIeE~tplv-tiktokx-origin.image?dr=14575&x-expires=1784451600&x-signature=c%2F7pdqeiaC4ak%2FffNOLKESKMy2Q%3D&t=4d5b0474&ps=13740610&shp=81f88b70&shcp=43f4a2f9&idc=my",
      "creator": "ghanatravel0",
      "caption": "",
      "likes": 572,
      "hashtags": [],
      "postedAt": "2025-11-20T04:13:39.000Z"
    },
    {
      "id": "tt_7649069056007474453",
      "platform": "tiktok",
      "url": "https://www.tiktok.com/@bolamontana/video/7649069056007474453",
      "thumbnail": "https://p16-common-sign.tiktokcdn-us.com/tos-alisg-p-0037/oUCKA8LJHFAAuEvAEqEDf9fCIAOBgP0wBcmTVR~tplv-tiktokx-origin.image?dr=9636&x-expires=1784451600&x-signature=gxXXq7BrweFkm4ewUpymANMcZ2c%3D&t=4d5b0474&ps=13740610&shp=81f88b70&shcp=43f4a2f9&idc=useast5",
      "creator": "bolamontana",
      "caption": "Let’s get into my 6-day itinerary in Ghana 🇬🇭\nSave for later 📌\n\n#ghanaitinerary #Ghanaliving #wheretovisit #vacation ",
      "likes": 566,
      "hashtags": [
        "ghanaitinerary",
        "ghanaliving",
        "wheretovisit",
        "vacation",
        "accraghana"
      ],
      "postedAt": "2026-06-08T16:54:45.000Z"
    }
  ]
}